fastapi_jwt_auth_md/__init__.py
fastapi_jwt_auth_md/auth_config.py
fastapi_jwt_auth_md/auth_jwt.py
fastapi_jwt_auth_md/config.py
fastapi_jwt_auth_md/exceptions.py
fastapi_jwt_auth_md-1.1.0.dist-info/LICENSE
fastapi_jwt_auth_md-1.1.0.dist-info/WHEEL
fastapi_jwt_auth_md-1.1.0.dist-info/METADATA
fastapi_jwt_auth_md-1.1.0.dist-info/RECORD
