Metadata-Version: 2.1
Name: fastapi-jwt-auth-md
Version: 1.1.0
Summary: FastAPI extension that provides JWT Auth support (secure, easy to use and lightweight)
Home-page: https://github.com/IndominusByte/fastapi-jwt-auth
Author: Nyoman Pradipta Dewantara
Author-email: nyomanpradipta120@gmail.com
Requires-Python: >=3.6
Classifier: Environment :: Web Environment
Classifier: Intended Audience :: Developers
Classifier: Programming Language :: Python :: 3
Classifier: Programming Language :: Python :: 3.6
Classifier: Programming Language :: Python :: 3.7
Classifier: Programming Language :: Python :: 3.8
Classifier: License :: OSI Approved :: MIT License
Classifier: Operating System :: OS Independent
Classifier: Topic :: Internet :: WWW/HTTP :: Dynamic Content
Classifier: Topic :: Software Development :: Libraries :: Python Modules
Requires-Dist: fastapi>=0.61.0
Requires-Dist: PyJWT>=1.7.1,<2.0.0
Requires-Dist: cryptography>=2.6,<4.0.0 ; extra == "asymmetric"
Requires-Dist: cryptography>=2.6,<4.0.0 ; extra == "dev"
Requires-Dist: uvicorn>=0.11.5,<0.12.0 ; extra == "dev"
Requires-Dist: mkdocs>=1.1.2,<2.0.0 ; extra == "doc"
Requires-Dist: mkdocs-material>=5.5.0,<6.0.0 ; extra == "doc"
Requires-Dist: markdown-include>=0.5.1,<0.6.0 ; extra == "doc"
Requires-Dist: pytest==6.0.1 ; extra == "test"
Requires-Dist: pytest-cov==2.10.0 ; extra == "test"
Requires-Dist: coveralls==2.1.2 ; extra == "test"
Project-URL: Documentation, https://indominusbyte.github.io/fastapi-jwt-auth/
Provides-Extra: asymmetric
Provides-Extra: dev
Provides-Extra: doc
Provides-Extra: test
